async_button.py
circuitpython_async_button-1.2.3.dist-info/LICENSE
circuitpython_async_button-1.2.3.dist-info/METADATA
circuitpython_async_button-1.2.3.dist-info/WHEEL
circuitpython_async_button-1.2.3.dist-info/top_level.txt
circuitpython_async_button-1.2.3.dist-info/RECORD
