Metadata-Version: 2.1
Name: circuitpython-async-button
Version: 1.2.3
Summary: a library for reading buttons using asyncio
Author-email: Adafruit Industries <circuitpython@adafruit.com>
License: MIT
Project-URL: Homepage, https://github.com/furbrain/CircuitPython_async_button
Keywords: adafruit,blinka,circuitpython,micropython,async_button,async,asyncio,countio,keypad,button,press
Classifier: Intended Audience :: Developers
Classifier: Topic :: Software Development :: Libraries
Classifier: Topic :: Software Development :: Embedded Systems
Classifier: Topic :: System :: Hardware
Classifier: License :: OSI Approved :: MIT License
Classifier: Programming Language :: Python :: 3
License-File: LICENSE
Requires-Dist: Adafruit-Blinka
Requires-Dist: adafruit-circuitpython-asyncio
Requires-Dist: adafruit-circuitpython-ticks
Provides-Extra: optional
Requires-Dist: sphinxcontrib-wavedrom ; extra == 'optional'
